mumaxXR/OvfEngine.py
mumaxXR/__init__.py
mumaxXR/scriptParser.py
mumaxxr-0.0.43.dist-info/LICENSE
mumaxxr-0.0.43.dist-info/METADATA
mumaxxr-0.0.43.dist-info/WHEEL
mumaxxr-0.0.43.dist-info/top_level.txt
mumaxxr-0.0.43.dist-info/RECORD
